lbvslitmus/__init__.py
lbvslitmus/benchmarking/__init__.py
lbvslitmus/benchmarking/benchmark.py
lbvslitmus/comparison/__init__.py
lbvslitmus/comparison/baseline_comparator.py
lbvslitmus/comparison/baseline_loader.py
lbvslitmus/comparison/comparison_visualization.py
lbvslitmus/datasets/__init__.py
lbvslitmus/datasets/dekois.py
lbvslitmus/datasets/downloader.py
lbvslitmus/datasets/dudad.py
lbvslitmus/datasets/dude.py
lbvslitmus/datasets/lit_pcba.py
lbvslitmus/datasets/muv.py
lbvslitmus/datasets/registry.py
lbvslitmus/datasets/welqrate.py
lbvslitmus/model_selection/__init__.py
lbvslitmus/model_selection/splitters/__init__.py
lbvslitmus/model_selection/splitters/maxmin_split.py
lbvslitmus/models/__init__.py
lbvslitmus/models/registry.py
lbvslitmus/models/similarity_search.py
lbvslitmus/scripts/__init__.py
lbvslitmus/scripts/canonicalize_smiles.py
lbvslitmus/scripts/data_filtration.py
lbvslitmus/scripts/data_preperation/lit_pcba_preparation.py
lbvslitmus/scripts/data_preperation/muv_preparation.py
lbvslitmus/scripts/data_preperation/verify_welqrate.py
lbvslitmus/scripts/data_preperation/welqrate_preparation.py
lbvslitmus/scripts/dekois.py
lbvslitmus/scripts/dudad_filtration.py
lbvslitmus/scripts/dude.py
lbvslitmus/scripts/generate_splits.py
lbvslitmus/scripts/migrate_dataset_to_v2_structure.py
lbvslitmus/visualization/__init__.py
lbvslitmus/visualization/bars.py
lbvslitmus/visualization/comparison.py
lbvslitmus/visualization/constants.py
lbvslitmus/visualization/distributions.py
lbvslitmus/visualization/heatmaps.py
lbvslitmus/visualization/plotter.py
lbvslitmus/visualization/utils.py
lbvslitmus-1.1.0.dist-info/WHEEL
lbvslitmus-1.1.0.dist-info/METADATA
lbvslitmus-1.1.0.dist-info/RECORD
