Metadata-Version: 2.3
Name: lbvslitmus
Version: 1.1.0
Summary: A modern, extendible platform for ligand-based virtual screening benchmarking. Automates data downloading, preprocessing, ML training, evaluation, and statistical analysis. Supports multiple datasets, molecular embeddings (fingerprints and pretrained neural networks), similarity search, and ML classifiers for identifying bioactive compounds.
Author: Kacper Szot, Maciej Nowakowski, Kinga Bunkowska, Jakub Adamczyk, AGH ML & Chemoinformatics Group
Author-email: Kacper Szot <kacperszot1@gmail.com>, Jakub Adamczyk <jadamczy@agh.edu.pl>, AGH ML & Chemoinformatics Group <jadamczy@agh.edu.pl>
Classifier: Programming Language :: Python :: 3
Classifier: License :: OSI Approved :: MIT License
Classifier: Operating System :: OS Independent
Classifier: Intended Audience :: Information Technology
Classifier: Intended Audience :: Science/Research
Classifier: Topic :: Scientific/Engineering :: Artificial Intelligence
Classifier: Topic :: Scientific/Engineering :: Chemistry
Classifier: Topic :: Scientific/Engineering :: Medical Science Apps.
Classifier: Topic :: Software Development :: Libraries :: Python Modules
Classifier: Typing :: Typed
Requires-Dist: hf-xet
Requires-Dist: huggingface-hub
Requires-Dist: joblib>=1.4.2
Requires-Dist: numpy>=1.20.0,<3
Requires-Dist: pandas<3
Requires-Dist: pyarrow
Requires-Dist: rdkit<=2024.9.5
Requires-Dist: requests>=2.32.3
Requires-Dist: scikit-fingerprints>=1.15.0
Requires-Dist: scikit-learn>=1.0.0,<2
Requires-Dist: scipy>=1.0.0,<2
Requires-Dist: tqdm>=4.0.0,<5
Requires-Dist: lightgbm>=4,<5
Requires-Dist: matplotlib
Requires-Dist: seaborn
Requires-Dist: pandas-stubs~=2.3.3
Requires-Dist: bbt-test>=0.0.2
Requires-Dist: pre-commit ; extra == 'dev'
Requires-Dist: pytest ; extra == 'dev'
Requires-Dist: pytest-cov ; extra == 'dev'
Requires-Dist: ruff ; extra == 'dev'
Requires-Python: >=3.11, <3.14
Provides-Extra: dev
